[
  {
    "id": "zuk-217512",
    "tipo": "Casa",
    "bairro": "Portão",
    "endereco": "R. Marcelino Iachinski, 30",
    "lance": 383675,
    "avaliacao": 1215733,
    "desconto": 68,
    "modalidade": "Leilão 2ª Praça",
    "encerramento": "2026-02-13",
    "ocupacao": "desconhecido",
    "link": "https://www.portalzuk.com.br/imovel/pr/curitiba/portao/rua-marcelino-iachinski-30/34940-217512"
  },
  {
    "id": "topo-32437",
    "tipo": "Apartamento",
    "bairro": "Água Verde",
    "endereco": "Ed. Filadélfia, R. Bento Viana, 958",
    "lance": 518414,
    "avaliacao": 1036829,
    "desconto": 50,
    "modalidade": "Judicial",
    "encerramento": "2026-02-10",
    "ocupacao": "desconhecido",
    "link": "https://topoleiloes.com.br/lote/32437/apartamento-ed-filadelfia-rua-bento-viana-958-agua-verde-curitibapr"
  },
  {
    "id": "zuk-216690",
    "tipo": "Casa",
    "bairro": "Alto Boqueirão",
    "endereco": "R. Julio Zandona, 888",
    "lance": 341800,
    "avaliacao": 683600,
    "desconto": 50,
    "modalidade": "Leilão 2ª Praça",
    "encerramento": "2026-02-19",
    "ocupacao": "ocupado",
    "link": "https://www.portalzuk.com.br/imovel/pr/curitiba/alto-boqueirao/rua-julio-zandona-888/35174-216690"
  },
  {
    "id": "2220646",
    "tipo": "Apartamento",
    "bairro": "Jardim Social",
    "endereco": "R. Cel. Temístocles de Souza Brasil, 208",
    "lance": 742152,
    "avaliacao": 1370000,
    "desconto": 46,
    "modalidade": "Compra Direta",
    "encerramento": null,
    "ocupacao": "ocupado",
    "link": "https://www.leilaoimovel.com.br/imovel/pr/curitiba/residencial-edificio-zurique-sem-direito-ao-uso-das-vagas-mencionadas-na-matricula-do-apartam-imovel-caixa-economica-federal-cef-2220646-10209029-venda-direta-caixa"
  },
  {
    "id": "2532349",
    "tipo": "Apartamento",
    "bairro": "Campo de Santana",
    "endereco": "R. Angelo Tozim, 1060 Apto 32",
    "lance": 126926,
    "avaliacao": 210000,
    "desconto": 40,
    "modalidade": "Compra Direta",
    "encerramento": null,
    "ocupacao": "desconhecido",
    "link": "https://www.leilaoimovel.com.br/imovel/pr/curitiba/residencial-res-cidade-de-padova-2-quartos-1-vaga-na-garagem-wc-sala-cozinha-imovel-caixa-economica-federal-cef-2532349-8555525253788-venda-direta-caixa"
  },
  {
    "id": "2108061",
    "tipo": "Casa",
    "bairro": "Campo de Santana",
    "endereco": "Cond. Res. Markzuk",
    "lance": 120541,
    "avaliacao": 200000,
    "desconto": 40,
    "modalidade": "Compra Direta",
    "encerramento": null,
    "ocupacao": "desconhecido",
    "link": "https://www.leilaoimovel.com.br/imovel/pr/curitiba/residencial-cond-res-markzuk-imovel-caixa-economica-federal-cef-2108061-1444418518931-venda-direta-caixa"
  },
  {
    "id": "2666355",
    "tipo": "Casa",
    "bairro": "CIC",
    "endereco": "Cond. Vitória 8",
    "lance": 151200,
    "avaliacao": 252000,
    "desconto": 40,
    "modalidade": "Leilão SFI",
    "encerramento": "2026-03-09",
    "ocupacao": "desconhecido",
    "link": "https://www.leilaoimovel.com.br/imovel/pr/curitiba/residencial-cond-vitoria-8-imovel-caixa-economica-federal-cef-2666355-8555513022166-venda-direta-caixa"
  },
  {
    "id": "2672134",
    "tipo": "Apartamento",
    "bairro": "Capão Raso",
    "endereco": "Res. Parque das Flores",
    "lance": 177000,
    "avaliacao": 295000,
    "desconto": 40,
    "modalidade": "Leilão SFI",
    "encerramento": "2026-03-16",
    "ocupacao": "desconhecido",
    "link": "https://www.leilaoimovel.com.br/imovel/pr/curitiba/residencial-res-parque-das-flores-quarto-1-vaga-na-garagem-wc-sala-cozinha-imovel-caixa-economica-federal-cef-2672134-8787706079136-venda-direta-caixa"
  },
  {
    "id": "2668259",
    "tipo": "Apartamento",
    "bairro": "Sítio Cercado",
    "endereco": "Res. Málaga",
    "lance": 172200,
    "avaliacao": 287000,
    "desconto": 40,
    "modalidade": "Leilão SFI",
    "encerramento": "2026-03-13",
    "ocupacao": "desconhecido",
    "link": "https://www.leilaoimovel.com.br/imovel/pr/curitiba/residencial-res-malaga-1-vaga-na-garagem-imovel-caixa-economica-federal-cef-2668259-1555525488647-venda-direta-caixa"
  }
]
